{
  "name": "beyondtrust-privileged-remote-access",
  "label": "BeyondTrust Privileged Remote Access",
  "description": "BeyondTrust Privileged Remote Access controls, manages, and audits privileged accounts and credentials. This enables just-in-time, zero trust access to on-premises and cloud resources by internal, external, and third-party users.",
  "publisher": "Fortinet",
  "cs_approved": true,
  "cs_compatible": true,
  "version": "1.0.0",
  "category": "Identity and Access Management",
  "help_online": "https://docs.fortinet.com/document/fortisoar/1.0.0/beyondtrust-privileged-remote-access/621/beyondtrust-privileged-remote-access-v1-0-0",
  "icon_small_name": "BeyondTrust-32X32.png",
  "icon_large_name": "BeyondTrust-80X80.png",
  "configuration": {
    "fields": [
      {
        "title": "Server URL",
        "name": "host",
        "type": "text",
        "visible": true,
        "editable": true,
        "required": true,
        "tooltip": "URL of the BeyondTrust server to connect and perform automated operations",

        "description": "URL of the BeyondTrust server to connect and perform automated operations."
      },
      {
        "title": "Client ID",
        "name": "client_id",
        "type": "text",
        "visible": true,
        "editable": true,
        "required": true,
        "tooltip": "Client ID of the BeyondTrust server to connect and perform automated operations.",
        "description": "Client ID of the BeyondTrust server to connect and perform automated operations. Refer to the section Accessing the BeyondTrust API for information on getting the client ID."
      },
      {
        "title": "Client Secret",
        "name": "client_secret",
        "type": "password",
        "visible": true,
        "editable": true,
        "required": true,
        "tooltip": "Client Secret used to access the BeyondTrust server to connect and perform the automated operations.",
        "description": "Client Secret used to access the BeyondTrust server to connect and perform the automated operations. Refer to the section Accessing the BeyondTrust API for information on getting the client secret."
      },
      {
        "title": "Verify SSL",
        "required": false,
        "editable": true,
        "visible": true,
        "type": "checkbox",
        "name": "verify_ssl",
        "value": true,
        "tooltip": "Specifies whether the SSL certificate for the server is to be verified or not. By default, this option is set to True.",
        "description": "Specifies whether the SSL certificate for the server is to be verified or not. By default, this option is set to True."
      }
    ]
  },
  "operations": [
    {
      "operation": "get_all_accounts_in_vault",
      "title": "Get Account List From Vault",
      "annotation": "get_all_accounts_in_vault",
      "description": "Retrieves a list of accounts from the BeyondTrust vault based on the filter criteria like name, type, account group, and any other input parameters you have specified.",
      "category": "investigation",
      "is_config_required": true,
      "visible": true,
      "enabled": true,
      "parameters": [
        {
          "name": "name",
          "title": "Account Name",
          "type": "text",
          "editable": true,
          "visible": true,
          "required": false,
          "tooltip": "Specify a name to retrieve a list of accounts from BeyondTrust vault that match the specified name.",
          "description": "(Optional) Specify a name to retrieve a list of accounts from BeyondTrust vault that match the specified name."
        },
        {
          "name": "include_personal",
          "title": "Include Personal",
          "type": "checkbox",
          "editable": true,
          "visible": true,
          "required": false,
          "value": false,
          "tooltip": "Select to include personal accounts in response. By default, it only retrieves shared accounts.",
          "description": "(Optional) Select to include personal accounts in response. By default, it only retrieves shared accounts."
        },
        {
          "name": "type",
          "title": "Account Type",
          "type": "select",
          "editable": true,
          "visible": true,
          "required": false,
          "tooltip": "Select an account type to retrieve from BeyondTrust vault.",
          "description": "(Optional) Select an account type to retrieve from BeyondTrust vault. You can choose from following options: \nPassword \nSSH",
          "options": [
            "Password",
            "SSH"
          ]
        },
        {
          "name": "account_group_id",
          "title": "Account Group ID",
          "type": "text",
          "editable": true,
          "visible": true,
          "required": false,
          "placeholder": "",
          "tooltip": "Specify an account group ID to filters results that include only those accounts that match the specified BeyondTrust vault account group.",
          "description": "(Optional) Specify an account group ID to filters results that include only those accounts that match the specified BeyondTrust vault account group."
        },
        {
          "name": "current_page",
          "title": "Page",
          "type": "integer",
          "editable": true,
          "visible": true,
          "required": false,
          "placeholder": "Page should be greater than 0",
          "tooltip": "Specify the page number from which to retrieve the records. Page value should be greater than 0.",
          "description": "(Optional) Specify the page number from which to retrieve the records. Page value should be greater than 0."
        },
        {
          "name": "per_page",
          "title": "Size",
          "type": "integer",
          "editable": true,
          "visible": true,
          "required": false,
          "placeholder": "Should be between 5 and 100.",
          "tooltip": "Specify the count of records that the operation should include for the current page.",
          "description": "(Optional) Specify the count of records that the operation should include for the current page. The value should be between 5 and 100."
        }
      ],
      "output_schema": [
        {
          "id": "",
          "type": "",
          "name": "",
          "account_group_id": "",
          "description": "",
          "personal": "",
          "account_policy": ""
        }
      ]
    },
    {
      "operation": "create_account_in_vault",
      "title": "Create Account in Vault",
      "annotation": "create_account_in_vault",
      "description": "Creates an account in BeyondTrust vault.",
      "category": "investigation",
      "is_config_required": true,
      "visible": true,
      "enabled": true,
      "parameters": [
        {
          "name": "name",
          "title": "Account Name",
          "type": "text",
          "editable": true,
          "visible": true,
          "required": true,
          "tooltip": "Specify a name for the BeyondTrust vault account to be created.",
          "description": "Specify a name for the BeyondTrust vault account to be created."
        },
        {
          "name": "username",
          "title": "Username",
          "type": "text",
          "editable": true,
          "visible": true,
          "required": true,
          "tooltip": "Specify the username to store in or retrieve from BeyondTrust vault.",
          "description": "Specify the username to store in or retrieve from BeyondTrust vault. The username can be used as follows: \nInject for authentication during remote access \nStore in Vault \nRetrieve from Vault"
        },
        {
          "name": "type",
          "title": "Account Type",
          "type": "select",
          "editable": true,
          "visible": true,
          "required": true,
          "tooltip": "Specify the type of account being created in BeyondTrust vault.",
          "description": "Specify the type of account being created in BeyondTrust vault. You can choose from following options: \nPassword: Select this option when storing login credentials in the form of a username and password. \nSSH: Select this option when storing login credentials in the form of an SSH key and passphrase.",
          "options": [
            "Password",
            "SSH"
          ],
          "onchange": {
            "Password": [
              {
                "name": "password",
                "title": "Password",
                "type": "password",
                "editable": true,
                "visible": true,
                "required": true,
                "tooltip": "Specify the password to retrieve from BeyondTrust vault and inject for a remote access.",
                "description": "Specify the password to retrieve from BeyondTrust vault and inject for a remote access. The password field is write-only."
              },
              {
                "name": "account_policy",
                "title": "Account Policy Name",
                "type": "text",
                "editable": true,
                "visible": true,
                "required": false,
                "tooltip": "Specify The code name of the account policy associated with the account. When left blank, the account policy is inherited from the account group.",
                "description": "(Optional) Specify The code name of the account policy associated with the account. When left blank, the account policy is inherited from the account group. If there is no account group, it is inherited from the global default."
              }
            ],
            "SSH": [
              {
                "name": "private_key",
                "title": "Private Key",
                "type": "textarea",
                "editable": true,
                "visible": true,
                "required": true,
                "tooltip": "Specify the private SSH key that to retrieve from BeyondTrust vault and inject for a remote access.",
                "description": "Specify the private SSH key that to retrieve from BeyondTrust vault and inject for a remote access."
              },
              {
                "name": "private_key_passphrase",
                "title": "Passphrase",
                "type": "text",
                "editable": true,
                "visible": true,
                "required": false,
                "tooltip": "Specify the passphrase that unlocks the specified private key.",
                "description": "(Optional) Specify the passphrase that unlocks the specified private key."
              },
              {
                "name": "private_key_public_cert",
                "title": "Public Certificate",
                "type": "textarea",
                "editable": true,
                "visible": true,
                "required": false,
                "tooltip": "Specify the public certificate to use for authentication.",
                "description": "(Optional) Specify the public certificate to use for authentication."
              }
            ]
          }
        },
        {
          "name": "description",
          "title": "Description",
          "type": "text",
          "editable": true,
          "visible": true,
          "required": false,
          "tooltip": "Specify a description of the account to be created in BeyondTrust vault.",
          "description": "(Optional) Specify a description of the account to be created in BeyondTrust vault."
        },
        {
          "name": "account_group_id",
          "title": "Account Group ID",
          "type": "text",
          "editable": true,
          "visible": true,
          "required": false,
          "tooltip": "Specify the unique identifier for the BeyondTrust Vault Account Group. It defaults to 1, the default Account Group.",
          "description": "(Optional) Specify the unique identifier for the BeyondTrust Vault Account Group. It defaults to 1, the default Account Group."
        }
      ],
      "output_schema": {
        "id": "",
        "type": "",
        "name": "",
        "username": "",
        "account_group_id": "",
        "description": "",
        "personal": "",
        "last_checkout_timestamp": "",
        "account_policy": ""
      }
    },
    {
      "operation": "delete_account_in_vault",
      "title": "Delete Account From Vault",
      "annotation": "delete_account_in_vault",
      "description": "Deletes an account from vault in BeyondTrust based on the account ID you have specified. NOTE: This action cannot delete personal account.",
      "category": "investigation",
      "is_config_required": true,
      "visible": true,
      "enabled": true,
      "parameters": [
        {
          "title": "Account ID",
          "name": "account_id",
          "type": "integer",
          "editable": true,
          "visible": true,
          "required": true,
          "tooltip": "Specify the ID of account to delete from the BeyondTrust vault.",
          "description": "Specify the ID of account to delete from the BeyondTrust vault."
        }
      ],
      "output_schema": {
        "status_code": "",
        "message": ""
      }
    },
    {
      "operation": "checkin_or_checkout_private_key_or_password",
      "title": "Checkin or Checkout Credentials From Vault",
      "annotation": "checkin_or_checkout_private_key_or_password",
      "description": "Checks in or checks out private key or password from the vault in BeyondTrust based on the account ID you have specified.",
      "category": "investigation",
      "is_config_required": true,
      "visible": true,
      "enabled": true,
      "parameters": [
        {
          "title": "Operation",
          "name": "operation",
          "type": "select",
          "editable": true,
          "visible": true,
          "required": true,
          "tooltip": "Select the operation to perform on credentials associated with the specified account ID.",
          "description": "Select the operation to perform on credentials associated with the specified account ID. You can choose from following options: \nCheck In \nCheck Out",
          "options": [
            "Check In",
            "Check Out"
          ]
        },
        {
          "title": "Account ID",
          "name": "account_id",
          "type": "integer",
          "editable": true,
          "visible": true,
          "required": true,
          "tooltip": "Specify the account ID whose credentials you are checking in or checking out from BeyondTrust vault.",
          "description": "Specify the account ID whose credentials you are checking in or checking out from BeyondTrust vault."
        }
      ],
      "conditional_output_schema": [
        {
          "condition": "{{operation === 'Check Out'}}",
          "output_schema": {
            "username": "",
            "type": "",
            "private_key": ""
          }
        },
        {
          "condition": "{{operation === 'Check In'}}",
          "output_schema": {
            "message": ""
          }
        }
      ]
    },
    {
      "operation": "get_all_vault_account_policies",
      "title": "Get Vault Account Policy List",
      "annotation": "get_all_vault_account_policies",
      "description": "Retrieves a list of account policies from BeyondTrust based on the filter criteria like name and pagination parameters you have specified.",
      "category": "investigation",
      "is_config_required": true,
      "visible": true,
      "enabled": true,
      "parameters": [
        {
          "name": "name",
          "title": "Policy Name",
          "type": "text",
          "editable": true,
          "visible": true,
          "required": false,
          "tooltip": "Specify a name of the account policy to filter the account policy list retrieved from BeyondTrust.",
          "description": "(Optional) Specify a name of the account policy to filter the account policy list retrieved from BeyondTrust. NOTE: Policy name matches are case-insensitive and exact. Partial matches are not returned."
        },
        {
          "name": "code_name",
          "title": "Policy Code Name",
          "type": "text",
          "editable": true,
          "visible": true,
          "required": false,
          "tooltip": "Specify a code name of the account policy to filter the account policy list retrieved from BeyondTrust.",
          "description": "(Optional) Specify a code name of the account policy to filter the account policy list retrieved from BeyondTrust. NOTE: Policy name matches are case-insensitive and exact. Partial matches are not returned."
        },
        {
          "name": "current_page",
          "title": "Page",
          "type": "integer",
          "editable": true,
          "visible": true,
          "required": false,
          "placeholder": "Page value should be greater than 0",
          "tooltip": "Specify the page number from which to retrieve the records.",
          "description": "(Optional) Specify the page number from which to retrieve the records. Page value should be greater than 0."
        },
        {
          "name": "per_page",
          "title": "Size",
          "type": "integer",
          "editable": true,
          "visible": true,
          "required": false,
          "placeholder": "Should be between 5 and 100.",
          "tooltip": "Specify the count of records that the operation should include for the current page.",
          "description": "(Optional) Specify the count of records that the operation should include for the current page. The value should be between 5 and 100."
        }
      ],
      "output_schema": [
        {
          "id": "",
          "code_name": "",
          "description": "",
          "auto_rotate_credentials": "",
          "allow_simultaneous_checkout": "",
          "name": "",
          "scheduled_password_rotation": "",
          "maximum_password_age": ""
        }
      ]
    },
    {
      "operation": "get_all_vault_account_groups",
      "title": "Get Vault Account Group List",
      "annotation": "get_all_vault_account_groups",
      "description": "Retrieves a list of account groups from BeyondTrust based on the filter criteria like name and pagination parameters you have specified.",
      "category": "investigation",
      "is_config_required": true,
      "visible": true,
      "enabled": true,
      "parameters": [
        {
          "name": "name",
          "title": "Group Name",
          "type": "text",
          "editable": true,
          "visible": true,
          "required": false,
          "tooltip": "Specify a name of the account group to filter the account group list retrieved from BeyondTrust.",
          "description": "(Optional) Specify a name of the account group to filter the account group list retrieved from BeyondTrust. NOTE: Group name matches are case-insensitive and exact. Partial matches are not returned."
        },
        {
          "name": "current_page",
          "title": "Page",
          "type": "integer",
          "editable": true,
          "visible": true,
          "required": false,
          "placeholder": "Page should be greater than 0",
          "tooltip": "Specify the page number from which to retrieve the records.",
          "description": "(Optional) Specify the page number from which to retrieve the records. Page value should be greater than 0."
        },
        {
          "name": "per_page",
          "title": "Size",
          "type": "integer",
          "editable": true,
          "visible": true,
          "required": false,
          "placeholder": "Should be between 5 and 100.",
          "tooltip": "Specify the count of records that the operation should include for the current page.",
          "description": "(Optional) Specify the count of records that the operation should include for the current page. The value should be between 5 and 100."
        }
      ],
      "output_schema": [
        {
          "id": "",
          "name": "",
          "description": "",
          "account_policy": ""
        }
      ]
    },
    {
      "operation": "get_all_users",
      "title": "Get User List",
      "annotation": "get_all_users",
      "description": "Retrieves a list of users from BeyondTrust based on the filter criteria like username, email ID, security provider ID, and other parameters you have specified.",
      "category": "investigation",
      "is_config_required": true,
      "visible": true,
      "enabled": true,
      "parameters": [
        {
          "name": "username",
          "title": "Username",
          "type": "text",
          "editable": true,
          "visible": true,
          "required": false,
          "tooltip": "Specify a username to retrieve a list of users from BeyondTrust vault that match the specified username.",
          "description": "(Optional) Specify a username to retrieve a list of users from BeyondTrust vault that match the specified username."
        },
        {
          "name": "email_address",
          "title": "Email ID",
          "type": "email",
          "editable": true,
          "visible": true,
          "required": false,
          "tooltip": "Specify an email ID to retrieve a list of users from BeyondTrust vault that match the specified email address.",
          "description": "(Optional) Specify an email ID to retrieve a list of users from BeyondTrust vault that match the specified email address."
        },
        {
          "name": "security_provider_id",
          "title": "Security Provider ID",
          "type": "text",
          "editable": true,
          "visible": true,
          "required": false,
          "tooltip": "Specify a security provider ID to retrieve a list of users from BeyondTrust vault that match the specified security provider ID.",
          "description": "(Optional) Specify a security provider ID to retrieve a list of users from BeyondTrust vault that match the specified security provider ID."
        },
        {
          "name": "current_page",
          "title": "Page",
          "type": "integer",
          "editable": true,
          "visible": true,
          "required": false,
          "placeholder": "Page should be greater than 0",
          "tooltip": "Specify the page number from which to retrieve the records.",
          "description": "(Optional) Specify the page number from which to retrieve the records. Page value should be greater than 0."
        },
        {
          "name": "per_page",
          "title": "Size",
          "type": "integer",
          "editable": true,
          "visible": true,
          "required": false,
          "placeholder": "Should be between 5 and 100.",
          "tooltip": "Specify the count of records that the operation should include for the current page.",
          "description": "(Optional) Specify the count of records that the operation should include for the current page. The value should be between 5 and 100."
        }
      ],
      "output_schema": [
        {
          "id": "",
          "username": "",
          "public_display_name": "",
          "password_reset_next_login": "",
          "email_address": "",
          "security_provider_id": "",
          "password_expiration": "",
          "failed_logins": "",
          "last_authentication": "",
          "created_at": "",
          "enabled": "",
          "preferred_email_language": "",
          "two_factor_required": ""
        }
      ]
    },
    {
      "operation": "get_all_vault_endpoints",
      "title": "Get Vault Endpoint List",
      "annotation": "get_all_vault_endpoints",
      "description": "Retrieves a list of vault endpoints from vault in BeyondTrust based on the filter criteria like name, hostname, domain name and other parameters you have specified.",
      "category": "investigation",
      "is_config_required": true,
      "visible": true,
      "enabled": true,
      "parameters": [
        {
          "name": "name",
          "title": "Endpoint Name",
          "type": "text",
          "editable": true,
          "visible": true,
          "required": false,
          "tooltip": "Specify an endpoint name to retrieve a list of endpoints from BeyondTrust vault that match the specified endpoint.",
          "description": "(Optional) Specify an endpoint name to retrieve a list of endpoints from BeyondTrust vault that match the specified endpoint."
        },
        {
          "name": "hostname",
          "title": "Host Name",
          "type": "text",
          "editable": true,
          "visible": true,
          "required": false,
          "tooltip": "Specify a hostname to retrieve a list of endpoints from BeyondTrust vault that match the specified hostname.",
          "description": "(Optional) Specify a hostname to retrieve a list of endpoints from BeyondTrust vault that match the specified hostname."
        },
        {
          "name": "domain_name",
          "title": "Domain Name",
          "type": "text",
          "editable": true,
          "visible": true,
          "required": false,
          "tooltip": "Specify a domain name to retrieve a list of endpoints from BeyondTrust vault that match the specified domain name.",
          "description": "(Optional) Specify a domain name to retrieve a list of endpoints from BeyondTrust vault that match the specified domain name."
        },
        {
          "name": "description",
          "title": "Description",
          "type": "text",
          "editable": true,
          "visible": true,
          "required": false,
          "tooltip": "Specify a description to retrieve a list of endpoints from BeyondTrust vault that match the specified description.",
          "description": "(Optional) Specify a description to retrieve a list of endpoints from BeyondTrust vault that match the specified description."
        },
        {
          "name": "current_page",
          "title": "Page",
          "type": "integer",
          "editable": true,
          "visible": true,
          "required": false,
          "placeholder": "Page should be greater than 0",
          "tooltip": "Specify the page number from which to retrieve the records.",
          "description": "(Optional) Specify the page number from which to retrieve the records. Page value should be greater than 0."
        },
        {
          "name": "per_page",
          "title": "Size",
          "type": "integer",
          "editable": true,
          "visible": true,
          "required": false,
          "placeholder": "Should be between 5 and 100.",
          "tooltip": "Specify the count of records that the operation should include for the current page.",
          "description": "(Optional) Specify the count of records that the operation should include for the current page. The value should be between 5 and 100."
        }
      ],
      "output_schema": []
    },
    {
      "operation": "get_all_vendor_groups",
      "title": "Get Vendor Group List",
      "annotation": "get_all_vendor_groups",
      "description": "Retrieves a list of vendor groups from BeyondTrust based on the filter criteria like name and pagination parameters you have specified.",
      "category": "investigation",
      "is_config_required": true,
      "visible": true,
      "enabled": true,
      "parameters": [
        {
          "name": "name",
          "title": "Vendor Group Name",
          "type": "text",
          "editable": true,
          "visible": true,
          "required": false,
          "tooltip": "Specify a name of the vendor group to retrieve a list of vendor groups from BeyondTrust vault that match the specified vendor group name.",
          "description": "(Optional) Specify a name of the vendor group to retrieve a list of vendor groups from BeyondTrust vault that match the specified vendor group name."
        },
        {
          "name": "current_page",
          "title": "Page",
          "type": "integer",
          "editable": true,
          "visible": true,
          "required": false,
          "placeholder": "Page should be greater than 0",
          "tooltip": "Specify the page number from which to retrieve the records.",
          "description": "(Optional) Specify the page number from which to retrieve the records. Page value should be greater than 0."
        },
        {
          "name": "per_page",
          "title": "Size",
          "type": "integer",
          "editable": true,
          "visible": true,
          "required": false,
          "placeholder": "Should be between 5 and 100.",
          "tooltip": "Specify the count of records that the operation should include for the current page.",
          "description": "(Optional) Specify the count of records that the operation should include for the current page. The value should be between 5 and 100."
        }
      ],
      "output_schema": [
        {
          "id": "",
          "name": "",
          "default_policy": "",
          "account_expiration": "",
          "user_added_notification_enabled": "",
          "user_expired_notification_enabled": "",
          "user_approval_enabled": "",
          "user_reactivation_enabled": "",
          "network_restrictions": [],
          "administrator_id": ""
        }
      ]
    },
    {
      "operation": "create_vendor_group",
      "title": "Create Vendor Group",
      "annotation": "create_vendor_group",
      "description": "Creates a vendor group in BeyondTrust based on the Vendor Group Name, Policy ID, and other parameters you have specified.",
      "category": "investigation",
      "is_config_required": true,
      "visible": true,
      "enabled": true,
      "parameters": [
        {
          "name": "name",
          "title": "Vendor Group Name",
          "type": "text",
          "editable": true,
          "visible": true,
          "required": true,
          "tooltip": "Specify a name for the BeyondTrust vendor group to be created.",
          "description": "Specify a name for the BeyondTrust vendor group to be created."
        },
        {
          "name": "default_policy",
          "title": "Policy ID",
          "type": "integer",
          "editable": true,
          "visible": true,
          "required": true,
          "tooltip": "Specify the group policy ID associated with the vendor group. NOTE: The group policy cannot grant administrative privileges.",
          "description": "Specify the group policy ID associated with the vendor group. NOTE: The group policy cannot grant administrative privileges."
        },
        {
          "name": "administrator_id",
          "title": "Administrator ID",
          "type": "integer",
          "editable": true,
          "visible": true,
          "required": true,
          "tooltip": "Specify the ID of the remote access user who receives emails as notifications or when user approvals are required. The user must have a valid email address, correct SMTP server Configurations, and notifications enabled to receive emails.",
          "description": "Specify the ID of the remote access user who receives emails as notifications or when user approvals are required. The user must have a valid email address, correct SMTP server Configurations, and notifications enabled to receive emails."
        },
        {
          "name": "account_expiration",
          "title": "Accounts Expire After",
          "type": "integer",
          "editable": true,
          "visible": true,
          "required": false,
          "value": 30,
          "placeholder": "Value should be between 1 and 365.",
          "tooltip": "Specify the duration(in days) after which the user accounts in the vendor group expire. By default, this parameter is set to 30 days.",
          "description": "(Optional) Specify the duration(in days) after which the user accounts in the vendor group expire. By default, this parameter is set to 30 days. The specified value should be between 1 and 365."
        },
        {
          "name": "user_added_notification_enabled",
          "title": "Notify the PRA User when a user is added",
          "type": "checkbox",
          "editable": true,
          "visible": true,
          "value": true,
          "tooltip": "Select to notify the Privileged Remote Access(PRA) user whenever a user is added to the vendor group.",
          "description": "Select to notify the Privileged Remote Access(PRA) user whenever a user is added to the vendor group. NOTE: If the Require PRA User approval to activate users checkbox is selected then this option must be selected."
        },
        {
          "name": "user_expired_notification_enabled",
          "title": "Notify the PRA User when a user has expired",
          "type": "checkbox",
          "editable": true,
          "visible": true,
          "value": true,
          "tooltip": "Select to notify the Privileged Remote Access (PRA) user when a user has expired in the vendor group. NOTE: Do not select this checkbox if the Notify the PRA User when a user is added checkbox is not selected.",
          "description": "Select to notify the Privileged Remote Access (PRA) user when a user has expired in the vendor group. NOTE: Do not select this checkbox if the Notify the PRA User when a user is added checkbox is not selected."
        },
        {
          "name": "user_approval_enabled",
          "title": "Require PRA User approval to activate users",
          "type": "checkbox",
          "editable": true,
          "visible": true,
          "value": false,
          "tooltip": "Select this option to require an approval by a Privileged Remote Access (PRA) user to activate users in the vendor group.",
          "description": "Select this option to require an approval by a Privileged Remote Access (PRA) user to activate users in the vendor group.",
          "onchange": {
            "true": [
              {
                "name": "user_reactivation_enabled",
                "title": "Require PRA User approval to extend or reactivate users",
                "type": "checkbox",
                "editable": true,
                "visible": true,
                "value": false,
                "tooltip": "Select this option to require an approval by a Privileged Remote Access (PRA) user to extend or reactivate users in the vendor group.",
                "description": "Select this option to require an approval by a Privileged Remote Access (PRA) user to extend or reactivate users in the vendor group."
              }
            ]
          }
        },
        {
          "name": "network_restrictions",
          "title": "Network Address Allow List",
          "type": "text",
          "editable": true,
          "visible": true,
          "required": false,
          "tooltip": "Specify the network address allow list related to network restrictions. you can specify multiple network addresses using comma separator.",
          "description": "(Optional) Specify the network address allow list related to network restrictions. you can specify multiple network addresses as comma-separated values."
        }
      ],
      "output_schema": {
        "id": "",
        "name": "",
        "default_policy": "",
        "account_expiration": "",
        "user_added_notification_enabled": "",
        "user_expired_notification_enabled": "",
        "user_approval_enabled": "",
        "user_reactivation_enabled": "",
        "network_restrictions": [],
        "administrator_id": ""
      }
    },
    {
      "operation": "get_vendor_group_by_id",
      "title": "Get Vendor Group Details",
      "annotation": "get_vendor_group_by_id",
      "description": "Retrieves the vendor group details from BeyondTrust based on the Vendor Group ID you have specified.",
      "category": "investigation",
      "is_config_required": true,
      "visible": true,
      "enabled": true,
      "parameters": [
        {
          "name": "group_id",
          "title": "Vendor Group ID",
          "type": "integer",
          "editable": true,
          "visible": true,
          "required": true,
          "tooltip": "Specify the ID of vendor group whose details are to be retrieved from BeyondTrust.",
          "description": "Specify the ID of vendor group whose details are to be retrieved from BeyondTrust."
        }
      ],
      "output_schema": {
        "id": "",
        "name": "",
        "default_policy": "",
        "account_expiration": "",
        "user_added_notification_enabled": "",
        "user_expired_notification_enabled": "",
        "user_approval_enabled": "",
        "user_reactivation_enabled": "",
        "network_restrictions": [],
        "administrator_id": ""
      }
    },
    {
      "operation": "update_vendor_group",
      "title": "Update Vendor Group",
      "annotation": "update_vendor_group",
      "description": "Updates a vendor group in BeyondTrust based on the Vendor Group ID, Vendor Group Name, Policy ID, and other parameters you have specified.",
      "category": "investigation",
      "is_config_required": true,
      "visible": true,
      "enabled": true,
      "parameters": [
        {
          "name": "group_id",
          "title": "Vendor Group ID",
          "type": "integer",
          "editable": true,
          "visible": true,
          "required": true,
          "tooltip": "Specify ID of vendor group to be updated.",
          "description": "Specify ID of vendor group to be updated."
        },
        {
          "name": "name",
          "title": "Vendor Group Name",
          "type": "text",
          "editable": true,
          "visible": true,
          "required": false,
          "tooltip": "Specify a new name for the BeyondTrust vendor group to be updated.",
          "description": "(Optional) Specify a new name for the BeyondTrust vendor group to be updated."
        },
        {
          "name": "default_policy",
          "title": "Policy ID",
          "type": "integer",
          "editable": true,
          "visible": true,
          "required": false,
          "tooltip": "Specify the group policy ID associated with the vendor group. Note: The group policy cannot grant administrative privileges.",
          "description": "(Optional) Specify the group policy ID associated with the vendor group. NOTE: The group policy cannot grant administrative privileges."
        },
        {
          "name": "account_expiration",
          "title": "Accounts Expire After",
          "type": "integer",
          "editable": true,
          "visible": true,
          "required": false,
          "value": 30,
          "placeholder": "Should be between 1 and 365",
          "tooltip": "Specify the duration(in days) after which the user accounts in the vendor group expire.",
          "description": "(Optional) Specify the duration(in days) after which the user accounts in the vendor group expire. By default, this parameter is set to 30 days. The specified value should be between 1 and 365."
        },
        {
          "name": "user_added_notification_enabled",
          "title": "Notify the PRA User when a user is added",
          "type": "checkbox",
          "editable": true,
          "visible": true,
          "value": true,
          "tooltip": "Select to notify the Privileged Remote Access(PRA) user whenever a user is added to the vendor group. NOTE: If the Require PRA User approval to activate users checkbox is selected then this option must be selected. In such cases, the Administrator ID parameter becomes mandatory and must be provided when enabling this feature.",
          "description": "Select to notify the Privileged Remote Access(PRA) user whenever a user is added to the vendor group. NOTE: If the Require PRA User approval to activate users checkbox is selected then this option must be selected. In such cases, the Administrator ID parameter becomes mandatory and must be provided when enabling this feature."
        },
        {
          "name": "user_expired_notification_enabled",
          "title": "Notify the PRA User when a user has expired",
          "type": "checkbox",
          "editable": true,
          "visible": true,
          "value": true,
          "tooltip": "Select to notify the Privileged Remote Access (PRA) user when a user has expired in the vendor group. NOTE: Do not select this checkbox if the Notify the PRA User when a user is added checkbox is not selected.",
          "description": "Select to notify the Privileged Remote Access (PRA) user when a user has expired in the vendor group. NOTE: Do not select this checkbox if the Notify the PRA User when a user is added checkbox is not selected."
        },
        {
          "name": "user_approval_enabled",
          "title": "Require PRA User approval to activate users",
          "type": "checkbox",
          "editable": true,
          "visible": true,
          "value": false,
          "tooltip": "Select this option to require an approval by a Privileged Remote Access (PRA) user to activate users in the vendor group. NOTE: Specify a value in the Administrator ID parameter if this checkbox is selected.",
          "description": "Select this option to require an approval by a Privileged Remote Access (PRA) user to activate users in the vendor group. NOTE: Specify a value in the Administrator ID parameter if this checkbox is selected.",
          "onchange": {
            "true": [
              {
                "name": "user_reactivation_enabled",
                "title": "Require PRA User approval to extend or reactivate users",
                "type": "checkbox",
                "editable": true,
                "visible": true,
                "value": false,
                "tooltip": "Select this option to require an approval by a Privileged Remote Access (PRA) user to extend or reactivate users in the vendor group.",
                "description": "Select this option to require an approval by a Privileged Remote Access (PRA) user to extend or reactivate users in the vendor group."
              }
            ]
          }
        },
        {
          "name": "administrator_id",
          "title": "Administrator ID",
          "type": "integer",
          "editable": true,
          "visible": true,
          "required": false,
          "tooltip": "Specify the ID of the remote access user who receives emails as notifications or when user approvals are required. The user must have a valid email address, correct SMTP server Configurations, and notifications enabled to receive emails.",
          "description": "(Optional) Specify the ID of the remote access user who receives emails as notifications or when user approvals are required. The user must have a valid email address, correct SMTP server Configurations, and notifications enabled to receive emails."
        },
        {
          "name": "network_restrictions",
          "title": "Network Address Allow List",
          "type": "text",
          "editable": true,
          "visible": true,
          "required": false,
          "tooltip": "Specify the network address allow list related to network restrictions. you can specify multiple network addresses as comma-separated values.",
          "description": "(Optional) Specify the network address allow list related to network restrictions. you can specify multiple network addresses as comma-separated values."
        }
      ],
      "output_schema": {
        "id": "",
        "name": "",
        "default_policy": "",
        "account_expiration": "",
        "user_added_notification_enabled": "",
        "user_expired_notification_enabled": "",
        "user_approval_enabled": "",
        "user_reactivation_enabled": "",
        "network_restrictions": [],
        "administrator_id": ""
      }
    },
    {
      "operation": "delete_vendor_group",
      "title": "Delete Vendor Group",
      "annotation": "delete_vendor_group",
      "description": "Deletes a specific vendor group from BeyondTrust based on the Vendor Group ID you have specified..",
      "category": "investigation",
      "is_config_required": true,
      "visible": true,
      "enabled": true,
      "parameters": [
        {
          "name": "group_id",
          "title": "Vendor Group ID",
          "type": "integer",
          "editable": true,
          "visible": true,
          "required": true,
          "tooltip": "Specify ID of vendor group which to be deleted from BeyondTrust.",
          "description": "Specify the ID of vendor group to be deleted from BeyondTrust."
        }
      ],
      "output_schema": {
        "status_code": "",
        "message": ""
      }
    },
    {
      "operation": "get_all_users_in_vendor_groups",
      "title": "Get User List in Vendor Group",
      "annotation": "get_all_users_in_vendor_groups",
      "description": "Retrieves a list of users in a vendor group based on the filter criteria like Vendor Group ID, pagination parameters, and other parameters you have specified.",
      "category": "investigation",
      "is_config_required": true,
      "visible": true,
      "enabled": true,
      "parameters": [
        {
          "name": "group_id",
          "title": "Vendor Group ID",
          "type": "text",
          "editable": true,
          "visible": true,
          "required": true,
          "tooltip": "Specify the ID of the vendor group from which the list of users is to be retrieved.",
          "description": "Specify the ID of the vendor group from which the list of users is to be retrieved."
        },
        {
          "name": "current_page",
          "title": "Page",
          "type": "integer",
          "editable": true,
          "visible": true,
          "required": false,
          "placeholder": "Page should be greater than 0",
          "tooltip": "Specify the page number from which to retrieve the records.",
          "description": "(Optional) Specify the page number from which to retrieve the records. Page value should be greater than 0."
        },
        {
          "name": "per_page",
          "title": "Size",
          "type": "integer",
          "editable": true,
          "visible": true,
          "required": false,
          "placeholder": "Should be between 5 and 100.",
          "tooltip": "Specify the count of records that the operation should include for the current page.",
          "description": "(Optional) Specify the count of records that the operation should include for the current page. The value should be between 5 and 100."
        }
      ],
      "output_schema": [
        {
          "id": "",
          "username": "",
          "public_display_name": "",
          "password_reset_next_login": "",
          "email_address": "",
          "account_disabled": "",
          "last_authenticated_date": "",
          "is_approved": "",
          "password_expiration": "",
          "preferred_email_language": "",
          "vendor_administrator": "",
          "is_expired": ""
        }
      ]
    },
    {
      "operation": "create_user_in_vendor_group",
      "title": "Create User in Vendor Group",
      "annotation": "create_user_in_vendor_group",
      "description": "Creates a user in a BeyondTrust vendor group based on the Vendor Group ID, Username, and other input parameters you have specified.",
      "category": "investigation",
      "is_config_required": true,
      "visible": true,
      "enabled": true,
      "parameters": [
        {
          "name": "group_id",
          "title": "Vendor Group ID",
          "type": "text",
          "editable": true,
          "visible": true,
          "required": true,
          "tooltip": "Specify the ID of the vendor group in which to create the user.",
          "description": "Specify the ID of the vendor group in which to create the user."
        },
        {
          "name": "username",
          "title": "Username",
          "type": "text",
          "editable": true,
          "visible": true,
          "required": true,
          "tooltip": "Specify the username of the user to be created in the vendor group.",
          "description": "Specify the username of the user to be created in the vendor group."
        },
        {
          "name": "public_display_name",
          "title": "Display Name",
          "type": "text",
          "editable": true,
          "visible": true,
          "required": true,
          "tooltip": "Specify the display name of the user to be created in the vendor group.",
          "description": "Specify the display name of the user to be created in the vendor group."
        },
        {
          "name": "password",
          "title": "Password",
          "type": "password",
          "editable": true,
          "visible": true,
          "required": true,
          "tooltip": "Specify the password of the user to be created in the vendor group.",
          "description": "Specify the password of the user to be created in the vendor group."
        },
        {
          "name": "email_address",
          "title": "Email Address",
          "type": "email",
          "editable": true,
          "visible": true,
          "required": true,
          "tooltip": "Specify the email address of the user to be created in the vendor group.",
          "description": "Specify the email address of the user to be created in the vendor group."
        },
        {
          "name": "password_never_expire",
          "title": "Password Never Expire",
          "type": "checkbox",
          "editable": true,
          "visible": true,
          "value": true,
          "tooltip": "Select this option for the user's password to never expire.",
          "description": "Select this option for the user's password to never expire.",
          "onchange": {
            "false": [
              {
                "name": "password_expiration",
                "title": "Password Expiration Date",
                "type": "datetime",
                "editable": true,
                "visible": true,
                "required": true,
                "tooltip": "Specify the date and time when the user's password expires.",
                "description": "Specify the date and time when the user's password expires."
              }
            ]
          }
        },
        {
          "name": "password_reset_next_login",
          "title": "Must Reset Password at Next Login",
          "type": "checkbox",
          "editable": true,
          "visible": true,
          "value": false,
          "tooltip": "Select this option to force the user to change their password on their next login.",
          "description": "Select this option to force the user to change their password on their next login. By default, this option is unchecked, i.e., it is set to false."
        },
        {
          "name": "account_disabled",
          "title": "Account Disabled",
          "type": "checkbox",
          "editable": true,
          "visible": true,
          "required": false,
          "value": "false",
          "tooltip": "Select this option to disable this user's account. If selected, the user is not allowed to login.",
          "description": "Select this option to disable this user's account. If selected, the user is not allowed to login."
        },
        {
          "name": "preferred_email_language",
          "title": "Preferred Email Language",
          "type": "text",
          "editable": true,
          "visible": true,
          "required": false,
          "placeholder": "For example en-us",
          "value": "en-us",
          "tooltip": "Specify the preferred email language of the user to be created in the vendor group.",
          "description": "(Optional) Specify the preferred email language of the user to be created in the vendor group. By default it is set to en-us."
        }
      ],
      "output_schema": {
        "id": "",
        "username": "",
        "public_display_name": "",
        "password_reset_next_login": "",
        "email_address": "",
        "account_disabled": "",
        "last_authenticated_date": "",
        "is_approved": "",
        "password_expiration": "",
        "preferred_email_language": "",
        "vendor_administrator": "",
        "is_expired": ""
      }
    },
    {
      "operation": "get_user_in_vendor_groups",
      "title": "Get User Details in Vendor Group",
      "annotation": "get_user_in_vendor_groups",
      "description": "Retrieves details of user in a BeyondTrust vendor group based on the User ID and Vendor Group ID you have specified.",
      "category": "investigation",
      "is_config_required": true,
      "visible": true,
      "enabled": true,
      "parameters": [
        {
          "name": "group_id",
          "title": "Vendor Group ID",
          "type": "text",
          "editable": true,
          "visible": true,
          "required": true,
          "tooltip": "Specify the ID of the vendor group from which to retrieve the list of users.",
          "description": "Specify the ID of the vendor group from which to retrieve the list of users."
        },
        {
          "name": "user_id",
          "title": "User ID",
          "type": "text",
          "editable": true,
          "visible": true,
          "required": true,
          "tooltip": "Specify the ID of the user whose details are to be retrieved.",
          "description": "Specify the ID of the user whose details are to be retrieved."
        }
      ],
      "output_schema": {
        "id": "",
        "username": "",
        "public_display_name": "",
        "password_reset_next_login": "",
        "email_address": "",
        "account_disabled": "",
        "last_authenticated_date": "",
        "is_approved": "",
        "password_expiration": "",
        "preferred_email_language": "",
        "vendor_administrator": "",
        "is_expired": ""
      }
    },
    {
      "operation": "remove_user_from_vendor_groups",
      "title": "Remove User from Vendor Group",
      "annotation": "remove_user_from_vendor_groups",
      "description": "Removes a user from a BeyondTrust vendor group based on the User ID and Vendor Group ID you have specified.",
      "category": "investigation",
      "is_config_required": true,
      "visible": true,
      "enabled": true,
      "parameters": [
        {
          "name": "group_id",
          "title": "Vendor Group ID",
          "type": "text",
          "editable": true,
          "visible": true,
          "required": true,
          "tooltip": "Specify the ID of the vendor group from which to remove the user.",
          "description": "Specify the ID of the vendor group from which to remove the user."
        },
        {
          "name": "user_id",
          "title": "User ID",
          "type": "text",
          "editable": true,
          "visible": true,
          "required": true,
          "tooltip": "Specify the ID of the user to remove from the specified vendor group.",
          "description": "Specify the ID of the user to remove from the specified vendor group."
        }
      ],
      "output_schema": {
        "status_code": "",
        "message": ""
      }
    },
    {
      "operation": "get_all_group_policies",
      "title": "Get Group Policy List",
      "annotation": "get_all_group_policies",
      "description": "Retrieves a list of group policies from BeyondTrust based on the filter criteria like Policy Name and pagination parameters you have specified.",
      "category": "investigation",
      "is_config_required": true,
      "visible": true,
      "enabled": true,
      "parameters": [
        {
          "name": "name",
          "title": "Policy Name",
          "type": "text",
          "editable": true,
          "visible": true,
          "required": false,
          "tooltip": "Specify the name of the group policy to be retrieved from BeyondTrust. NOTE: Policy name matches are case-insensitive and exact. Partial matches are not returned.",
          "description": "(Optional) Specify the name of the group policy to be retrieved from BeyondTrust. NOTE: Policy name matches are case-insensitive and exact. Partial matches are not returned."
        },
        {
          "name": "current_page",
          "title": "Page",
          "type": "integer",
          "editable": true,
          "visible": true,
          "required": false,
          "placeholder": "Page should be greater than 0",
          "tooltip": "Specify the page number from which to retrieve the records.",
          "description": "(Optional) Specify the page number from which to retrieve the records. Page value should be greater than 0."
        },
        {
          "name": "per_page",
          "title": "Size",
          "type": "integer",
          "editable": true,
          "visible": true,
          "required": false,
          "placeholder": "Should be between 5 and 100.",
          "tooltip": "Specify the count of records that the operation should include for the current page.",
          "description": "(Optional) Specify the count of records that the operation should include for the current page. The value should be between 5 and 100."
        }
      ],
      "output_schema": [
        {
          "id": "",
          "default_jump_item_role_id": "",
          "private_jump_item_role_id": "",
          "inferior_jump_item_role_id": "",
          "unassigned_jump_item_role_id": "",
          "name": "",
          "perm_share_other_team": "",
          "perm_extended_availability_mode_allowed": "",
          "perm_jump_client": "",
          "perm_local_jump": "",
          "perm_remote_jump": "",
          "perm_remote_vnc": "",
          "perm_remote_rdp": "",
          "perm_shell_jump": "",
          "perm_session_idle_timeout": "",
          "perm_edit_external_key": "",
          "perm_collaborate": "",
          "perm_collaborate_control": "",
          "perm_invite_external_user": "",
          "perm_protocol_tunnel": "",
          "perm_access_allowed": "",
          "perm_web_jump": "",
          "access_perm_status": ""
        }
      ]
    }
  ]
}